funfetch/__init__.py
funfetch/client.py
funfetch/converter.py
funfetch/errors.py
funfetch/model.py
funfetch/server.py
funfetch/utils.py
funfetch-0.0.1.dist-info/LICENSE
funfetch-0.0.1.dist-info/METADATA
funfetch-0.0.1.dist-info/WHEEL
funfetch-0.0.1.dist-info/top_level.txt
funfetch-0.0.1.dist-info/RECORD
