Metadata-Version: 2.1
Name: funfetch
Version: 0.0.1
Summary: Remote execution of a simple function on the server
Home-page: https://github.com/decave27/funfetch
Author: decave27
Author-email: decave27@gmail.com
License: MIT
Project-URL: Source, https://github.com/decave27/funfetch
Project-URL: Tracker, https://github.com/decave27/funfetch/issues
Keywords: aiohttp,ipc,request,fetch
Platform: UNKNOWN
Classifier: Environment :: Console
Classifier: Programming Language :: Python :: 3.7
Classifier: Programming Language :: Python :: 3.8
Classifier: Programming Language :: Python :: Implementation
Classifier: Programming Language :: Python :: Implementation :: CPython
Requires-Python: >=3.7
Requires-Dist: aiohttp
Requires-Dist: astunparse
